{
    "frame_index": 589,
    "viewport_width": 1920,
    "viewport_height": 1080,
    "2dPlayerTracking": {
        "people": [
            {
                "left": 1265,
                "top": 678,
                "right": 1452,
                "bottom": 913,
                "team": "Time 0"
            },
            {
                "left": 590,
                "top": 67,
                "right": 701,
                "bottom": 285,
                "team": "Time 1"
            }
        ]
    }
}